__init__.py
brat_parser.py
mendelai_brat_parser-0.0.4.dist-info/METADATA
mendelai_brat_parser-0.0.4.dist-info/WHEEL
mendelai_brat_parser-0.0.4.dist-info/top_level.txt
mendelai_brat_parser-0.0.4.dist-info/RECORD
