Metadata-Version: 2.1
Name: mendelai-brat-parser
Version: 0.0.4
Summary: BRAT Parser
Home-page: https://github.com/mendelhealth/brat-parser
Author: Khaled Essam
Author-email: khaled.essam@mendel.ai
License: UNKNOWN
Platform: UNKNOWN
Classifier: Programming Language :: Python :: 3
Classifier: Operating System :: OS Independent
Requires-Python: >=3.6
